[
  {"id":"hsk3_001","character":"阿姨","pinyin":"āyí","translation":"aunt, auntie","hsk_level":3,"part_of_speech":"noun","example_sentence":{"chinese":"阿姨来我家了。","pinyin":"āyí lái wǒ jiā le.","english":"Auntie came to my house."}},
  {"id":"hsk3_002","character":"啊","pinyin":"a","translation":"ah, oh (interjection)","hsk_level":3,"part_of_speech":"interjection","example_sentence":{"chinese":"啊，原来是你！","pinyin":"a, yuánlái shì nǐ!","english":"Oh, so it's you!"}},
  {"id":"hsk3_003","character":"矮","pinyin":"ǎi","translation":"short (height)","hsk_level":3,"part_of_speech":"adjective","example_sentence":{"chinese":"他比我矮。","pinyin":"tā bǐ wǒ ǎi.","english":"He is shorter than me."}},
  {"id":"hsk3_004","character":"爱好","pinyin":"àihào","translation":"hobby, interest","hsk_level":3,"part_of_speech":"noun","example_sentence":{"chinese":"你的爱好是什么？","pinyin":"nǐ de àihào shì shénme?","english":"What is your hobby?"}},
  {"id":"hsk3_005","character":"安静","pinyin":"ānjìng","translation":"quiet, peaceful","hsk_level":3,"part_of_speech":"adjective","example_sentence":{"chinese":"图书馆很安静。","pinyin":"túshūguǎn hěn ānjìng.","english":"The library is very quiet."}},
  {"id":"hsk3_006","character":"把","pinyin":"bǎ","translation":"(disposal particle), to hold","hsk_level":3,"part_of_speech":"preposition","example_sentence":{"chinese":"把书放在桌子上。","pinyin":"bǎ shū fàng zài zhuōzi shàng.","english":"Put the book on the desk."}},
  {"id":"hsk3_007","character":"班","pinyin":"bān","translation":"class, shift","hsk_level":3,"part_of_speech":"noun","example_sentence":{"chinese":"我们班有三十个学生。","pinyin":"wǒmen bān yǒu sānshí gè xuéshēng.","english":"Our class has thirty students."}},
  {"id":"hsk3_008","character":"搬","pinyin":"bān","translation":"to move (house/heavy objects)","hsk_level":3,"part_of_speech":"verb","example_sentence":{"chinese":"我们搬家了。","pinyin":"wǒmen bān jiā le.","english":"We moved house."}},
  {"id":"hsk3_009","character":"半","pinyin":"bàn","translation":"half","hsk_level":3,"part_of_speech":"numeral","example_sentence":{"chinese":"三点半。","pinyin":"sān diǎn bàn.","english":"Three thirty."}},
  {"id":"hsk3_010","character":"办法","pinyin":"bànfǎ","translation":"method, way, solution","hsk_level":3,"part_of_speech":"noun","example_sentence":{"chinese":"有什么办法？","pinyin":"yǒu shénme bànfǎ?","english":"Is there any solution?"}},
  {"id":"hsk3_011","character":"办公室","pinyin":"bàngōngshì","translation":"office","hsk_level":3,"part_of_speech":"noun","example_sentence":{"chinese":"经理在办公室。","pinyin":"jīnglǐ zài bàngōngshì.","english":"The manager is in the office."}},
  {"id":"hsk3_012","character":"帮忙","pinyin":"bāngmáng","translation":"to help, to lend a hand","hsk_level":3,"part_of_speech":"verb","example_sentence":{"chinese":"请帮忙。","pinyin":"qǐng bāngmáng.","english":"Please help."}},
  {"id":"hsk3_013","character":"包","pinyin":"bāo","translation":"bag, package","hsk_level":3,"part_of_speech":"noun","example_sentence":{"chinese":"我的包在哪里？","pinyin":"wǒ de bāo zài nǎlǐ?","english":"Where is my bag?"}},
  {"id":"hsk3_014","character":"饱","pinyin":"bǎo","translation":"full (from eating)","hsk_level":3,"part_of_speech":"adjective","example_sentence":{"chinese":"我吃饱了。","pinyin":"wǒ chī bǎo le.","english":"I am full."}},
  {"id":"hsk3_015","character":"北方","pinyin":"běifāng","translation":"north, northern region","hsk_level":3,"part_of_speech":"noun","example_sentence":{"chinese":"北方冬天很冷。","pinyin":"běifāng dōngtiān hěn lěng.","english":"The north is very cold in winter."}},
  {"id":"hsk3_016","character":"被","pinyin":"bèi","translation":"(passive particle), by","hsk_level":3,"part_of_speech":"preposition","example_sentence":{"chinese":"书被他拿走了。","pinyin":"shū bèi tā ná zǒu le.","english":"The book was taken by him."}},
  {"id":"hsk3_017","character":"鼻子","pinyin":"bízi","translation":"nose","hsk_level":3,"part_of_speech":"noun","example_sentence":{"chinese":"他的鼻子很大。","pinyin":"tā de bízi hěn dà.","english":"His nose is very big."}},
  {"id":"hsk3_018","character":"比较","pinyin":"bǐjiào","translation":"to compare, comparatively","hsk_level":3,"part_of_speech":"verb","example_sentence":{"chinese":"这个比较贵。","pinyin":"zhège bǐjiào guì.","english":"This is comparatively expensive."}},
  {"id":"hsk3_019","character":"比赛","pinyin":"bǐsài","translation":"competition, match","hsk_level":3,"part_of_speech":"noun","example_sentence":{"chinese":"今天有比赛。","pinyin":"jīntiān yǒu bǐsài.","english":"There is a competition today."}},
  {"id":"hsk3_020","character":"笔记本","pinyin":"bǐjìběn","translation":"notebook","hsk_level":3,"part_of_speech":"noun","example_sentence":{"chinese":"我用笔记本记笔记。","pinyin":"wǒ yòng bǐjìběn jì bǐjì.","english":"I use a notebook to take notes."}},
  {"id":"hsk3_021","character":"必须","pinyin":"bìxū","translation":"must, have to","hsk_level":3,"part_of_speech":"adverb","example_sentence":{"chinese":"你必须去。","pinyin":"nǐ bìxū qù.","english":"You must go."}},
  {"id":"hsk3_022","character":"变化","pinyin":"biànhuà","translation":"change, variation","hsk_level":3,"part_of_speech":"noun","example_sentence":{"chinese":"城市变化很大。","pinyin":"chéngshì biànhuà hěn dà.","english":"The city has changed a lot."}},
  {"id":"hsk3_023","character":"别人","pinyin":"biérén","translation":"other people, others","hsk_level":3,"part_of_speech":"noun","example_sentence":{"chinese":"别影响别人。","pinyin":"bié yǐngxiǎng biérén.","english":"Don't affect others."}},
  {"id":"hsk3_024","character":"冰箱","pinyin":"bīngxiāng","translation":"refrigerator","hsk_level":3,"part_of_speech":"noun","example_sentence":{"chinese":"水果在冰箱里。","pinyin":"shuǐguǒ zài bīngxiāng lǐ.","english":"The fruit is in the refrigerator."}},
  {"id":"hsk3_025","character":"菜单","pinyin":"càidān","translation":"menu","hsk_level":3,"part_of_speech":"noun","example_sentence":{"chinese":"请给我菜单。","pinyin":"qǐng gěi wǒ càidān.","english":"Please give me the menu."}},
  {"id":"hsk3_026","character":"参加","pinyin":"cānjiā","translation":"to participate, to join","hsk_level":3,"part_of_speech":"verb","example_sentence":{"chinese":"我参加了比赛。","pinyin":"wǒ cānjiā le bǐsài.","english":"I participated in the competition."}},
  {"id":"hsk3_027","character":"草","pinyin":"cǎo","translation":"grass, straw","hsk_level":3,"part_of_speech":"noun","example_sentence":{"chinese":"公园里有很多草。","pinyin":"gōngyuán lǐ yǒu hěn duō cǎo.","english":"There is a lot of grass in the park."}},
  {"id":"hsk3_028","character":"层","pinyin":"céng","translation":"floor, layer, storey","hsk_level":3,"part_of_speech":"measure_word","example_sentence":{"chinese":"我住在五层。","pinyin":"wǒ zhù zài wǔ céng.","english":"I live on the fifth floor."}},
  {"id":"hsk3_029","character":"差","pinyin":"chà","translation":"bad, poor, lacking","hsk_level":3,"part_of_speech":"adjective","example_sentence":{"chinese":"这个质量很差。","pinyin":"zhège zhìliàng hěn chà.","english":"This quality is very poor."}},
  {"id":"hsk3_030","character":"超市","pinyin":"chāoshì","translation":"supermarket","hsk_level":3,"part_of_speech":"noun","example_sentence":{"chinese":"我去超市买东西。","pinyin":"wǒ qù chāoshì mǎi dōngxi.","english":"I go to the supermarket to buy things."}},
  {"id":"hsk3_031","character":"衬衫","pinyin":"chènshān","translation":"shirt","hsk_level":3,"part_of_speech":"noun","example_sentence":{"chinese":"他穿白衬衫。","pinyin":"tā chuān bái chènshān.","english":"He wears a white shirt."}},
  {"id":"hsk3_032","character":"成绩","pinyin":"chéngjì","translation":"result, grade, achievement","hsk_level":3,"part_of_speech":"noun","example_sentence":{"chinese":"他的成绩很好。","pinyin":"tā de chéngjì hěn hǎo.","english":"His grades are very good."}},
  {"id":"hsk3_033","character":"城市","pinyin":"chéngshì","translation":"city","hsk_level":3,"part_of_speech":"noun","example_sentence":{"chinese":"北京是大城市。","pinyin":"Běijīng shì dà chéngshì.","english":"Beijing is a big city."}},
  {"id":"hsk3_034","character":"迟到","pinyin":"chídào","translation":"to be late, to arrive late","hsk_level":3,"part_of_speech":"verb","example_sentence":{"chinese":"对不起，我迟到了。","pinyin":"duìbuqǐ, wǒ chídào le.","english":"Sorry, I am late."}},
  {"id":"hsk3_035","character":"除了","pinyin":"chúle","translation":"except, besides, apart from","hsk_level":3,"part_of_speech":"preposition","example_sentence":{"chinese":"除了他，大家都来了。","pinyin":"chúle tā, dàjiā dōu lái le.","english":"Everyone came except him."}},
  {"id":"hsk3_036","character":"船","pinyin":"chuán","translation":"ship, boat","hsk_level":3,"part_of_speech":"noun","example_sentence":{"chinese":"我坐船去。","pinyin":"wǒ zuò chuán qù.","english":"I travel by boat."}},
  {"id":"hsk3_037","character":"春","pinyin":"chūn","translation":"spring (season)","hsk_level":3,"part_of_speech":"noun","example_sentence":{"chinese":"春天来了。","pinyin":"chūntiān lái le.","english":"Spring has come."}},
  {"id":"hsk3_038","character":"词典","pinyin":"cídiǎn","translation":"dictionary","hsk_level":3,"part_of_speech":"noun","example_sentence":{"chinese":"用词典查一下。","pinyin":"yòng cídiǎn chá yīxià.","english":"Look it up in the dictionary."}},
  {"id":"hsk3_039","character":"聪明","pinyin":"cōngming","translation":"clever, smart, intelligent","hsk_level":3,"part_of_speech":"adjective","example_sentence":{"chinese":"这个孩子很聪明。","pinyin":"zhège háizi hěn cōngming.","english":"This child is very clever."}},
  {"id":"hsk3_040","character":"打扫","pinyin":"dǎsǎo","translation":"to clean, to sweep","hsk_level":3,"part_of_speech":"verb","example_sentence":{"chinese":"我打扫房间。","pinyin":"wǒ dǎsǎo fángjiān.","english":"I clean the room."}},
  {"id":"hsk3_041","character":"打算","pinyin":"dǎsuàn","translation":"to plan, to intend","hsk_level":3,"part_of_speech":"verb","example_sentence":{"chinese":"你打算做什么？","pinyin":"nǐ dǎsuàn zuò shénme?","english":"What do you plan to do?"}},
  {"id":"hsk3_042","character":"带","pinyin":"dài","translation":"to bring, to carry, belt","hsk_level":3,"part_of_speech":"verb","example_sentence":{"chinese":"记得带雨伞。","pinyin":"jìde dài yǔsǎn.","english":"Remember to bring an umbrella."}},
  {"id":"hsk3_043","character":"担心","pinyin":"dānxīn","translation":"to worry, to be anxious","hsk_level":3,"part_of_speech":"verb","example_sentence":{"chinese":"不要担心。","pinyin":"bùyào dānxīn.","english":"Don't worry."}},
  {"id":"hsk3_044","character":"蛋糕","pinyin":"dàngāo","translation":"cake","hsk_level":3,"part_of_speech":"noun","example_sentence":{"chinese":"生日蛋糕很好吃。","pinyin":"shēngrì dàngāo hěn hǎochī.","english":"The birthday cake is delicious."}},
  {"id":"hsk3_045","character":"当然","pinyin":"dāngrán","translation":"of course, naturally","hsk_level":3,"part_of_speech":"adverb","example_sentence":{"chinese":"当然可以。","pinyin":"dāngrán kěyǐ.","english":"Of course it's okay."}},
  {"id":"hsk3_046","character":"地","pinyin":"de","translation":"(adverbial particle)","hsk_level":3,"part_of_speech":"particle","example_sentence":{"chinese":"慢慢地走。","pinyin":"mànmàn de zǒu.","english":"Walk slowly."}},
  {"id":"hsk3_047","character":"灯","pinyin":"dēng","translation":"lamp, light","hsk_level":3,"part_of_speech":"noun","example_sentence":{"chinese":"请开灯。","pinyin":"qǐng kāi dēng.","english":"Please turn on the light."}},
  {"id":"hsk3_048","character":"地方","pinyin":"dìfang","translation":"place, location","hsk_level":3,"part_of_speech":"noun","example_sentence":{"chinese":"你去什么地方？","pinyin":"nǐ qù shénme dìfang?","english":"Where are you going?"}},
  {"id":"hsk3_049","character":"地铁","pinyin":"dìtiě","translation":"subway, metro","hsk_level":3,"part_of_speech":"noun","example_sentence":{"chinese":"我坐地铁去。","pinyin":"wǒ zuò dìtiě qù.","english":"I go by subway."}},
  {"id":"hsk3_050","character":"地图","pinyin":"dìtú","translation":"map","hsk_level":3,"part_of_speech":"noun","example_sentence":{"chinese":"我看地图找路。","pinyin":"wǒ kàn dìtú zhǎo lù.","english":"I look at the map to find the way."}},
  {"id":"hsk3_051","character":"电梯","pinyin":"diàntī","translation":"elevator, lift","hsk_level":3,"part_of_speech":"noun","example_sentence":{"chinese":"坐电梯上楼。","pinyin":"zuò diàntī shàng lóu.","english":"Take the elevator upstairs."}},
  {"id":"hsk3_052","character":"电子邮件","pinyin":"diànzǐ yóujiàn","translation":"email","hsk_level":3,"part_of_speech":"noun","example_sentence":{"chinese":"发电子邮件给我。","pinyin":"fā diànzǐ yóujiàn gěi wǒ.","english":"Send me an email."}},
  {"id":"hsk3_053","character":"东","pinyin":"dōng","translation":"east","hsk_level":3,"part_of_speech":"noun","example_sentence":{"chinese":"往东走。","pinyin":"wǎng dōng zǒu.","english":"Walk east."}},
  {"id":"hsk3_054","character":"冬","pinyin":"dōng","translation":"winter","hsk_level":3,"part_of_speech":"noun","example_sentence":{"chinese":"冬天很冷。","pinyin":"dōngtiān hěn lěng.","english":"Winter is very cold."}},
  {"id":"hsk3_055","character":"动物","pinyin":"dòngwù","translation":"animal","hsk_level":3,"part_of_speech":"noun","example_sentence":{"chinese":"动物园有很多动物。","pinyin":"dòngwùyuán yǒu hěn duō dòngwù.","english":"The zoo has many animals."}},
  {"id":"hsk3_056","character":"短","pinyin":"duǎn","translation":"short (length/duration)","hsk_level":3,"part_of_speech":"adjective","example_sentence":{"chinese":"她的头发很短。","pinyin":"tā de tóufa hěn duǎn.","english":"Her hair is very short."}},
  {"id":"hsk3_057","character":"段","pinyin":"duàn","translation":"paragraph, section, period","hsk_level":3,"part_of_speech":"measure_word","example_sentence":{"chinese":"第一段很难。","pinyin":"dì yī duàn hěn nán.","english":"The first paragraph is very difficult."}},
  {"id":"hsk3_058","character":"锻炼","pinyin":"duànliàn","translation":"to exercise, to train","hsk_level":3,"part_of_speech":"verb","example_sentence":{"chinese":"每天锻炼身体。","pinyin":"měi tiān duànliàn shēntǐ.","english":"Exercise every day."}},
  {"id":"hsk3_059","character":"多么","pinyin":"duōme","translation":"how, what a (exclamation)","hsk_level":3,"part_of_speech":"adverb","example_sentence":{"chinese":"多么美的风景！","pinyin":"duōme měi de fēngjǐng!","english":"What a beautiful scenery!"}},
  {"id":"hsk3_060","character":"饿","pinyin":"è","translation":"hungry","hsk_level":3,"part_of_speech":"adjective","example_sentence":{"chinese":"我很饿。","pinyin":"wǒ hěn è.","english":"I am very hungry."}},
  {"id":"hsk3_061","character":"不但……而且……","pinyin":"búdàn…érqiě…","translation":"not only...but also","hsk_level":3,"part_of_speech":"conjunction","example_sentence":{"chinese":"他不但聪明而且勤劳。","pinyin":"tā búdàn cōngming érqiě qínláo.","english":"He is not only clever but also hardworking."}},
  {"id":"hsk3_062","character":"耳朵","pinyin":"ěrduo","translation":"ear(s)","hsk_level":3,"part_of_speech":"noun","example_sentence":{"chinese":"他的耳朵很好。","pinyin":"tā de ěrduo hěn hǎo.","english":"He has good ears."}},
  {"id":"hsk3_063","character":"发","pinyin":"fā","translation":"to send, to issue","hsk_level":3,"part_of_speech":"verb","example_sentence":{"chinese":"发短信。","pinyin":"fā duǎnxìn.","english":"Send a text message."}},
  {"id":"hsk3_064","character":"发烧","pinyin":"fāshāo","translation":"to have a fever","hsk_level":3,"part_of_speech":"verb","example_sentence":{"chinese":"他发烧了。","pinyin":"tā fāshāo le.","english":"He has a fever."}},
  {"id":"hsk3_065","character":"发现","pinyin":"fāxiàn","translation":"to discover, to find","hsk_level":3,"part_of_speech":"verb","example_sentence":{"chinese":"我发现了一个问题。","pinyin":"wǒ fāxiàn le yī gè wèntí.","english":"I discovered a problem."}},
  {"id":"hsk3_066","character":"方便","pinyin":"fāngbiàn","translation":"convenient","hsk_level":3,"part_of_speech":"adjective","example_sentence":{"chinese":"地铁很方便。","pinyin":"dìtiě hěn fāngbiàn.","english":"The subway is very convenient."}},
  {"id":"hsk3_067","character":"放","pinyin":"fàng","translation":"to put, to place, to release","hsk_level":3,"part_of_speech":"verb","example_sentence":{"chinese":"把书放在这里。","pinyin":"bǎ shū fàng zài zhèlǐ.","english":"Put the book here."}},
  {"id":"hsk3_068","character":"放心","pinyin":"fàngxīn","translation":"to be at ease, don't worry","hsk_level":3,"part_of_speech":"verb","example_sentence":{"chinese":"放心，没问题。","pinyin":"fàngxīn, méi wèntí.","english":"Don't worry, no problem."}},
  {"id":"hsk3_069","character":"分","pinyin":"fēn","translation":"minute, point, fraction","hsk_level":3,"part_of_speech":"noun","example_sentence":{"chinese":"三点十分。","pinyin":"sān diǎn shí fēn.","english":"Three ten."}},
  {"id":"hsk3_070","character":"附近","pinyin":"fùjìn","translation":"nearby, in the vicinity","hsk_level":3,"part_of_speech":"noun","example_sentence":{"chinese":"附近有超市吗？","pinyin":"fùjìn yǒu chāoshì ma?","english":"Is there a supermarket nearby?"}},
  {"id":"hsk3_071","character":"复习","pinyin":"fùxí","translation":"to review, to revise","hsk_level":3,"part_of_speech":"verb","example_sentence":{"chinese":"我复习功课。","pinyin":"wǒ fùxí gōngkè.","english":"I review my lessons."}},
  {"id":"hsk3_072","character":"干净","pinyin":"gānjìng","translation":"clean, neat","hsk_level":3,"part_of_speech":"adjective","example_sentence":{"chinese":"房间很干净。","pinyin":"fángjiān hěn gānjìng.","english":"The room is very clean."}},
  {"id":"hsk3_073","character":"感兴趣","pinyin":"gǎn xìngqù","translation":"to be interested in","hsk_level":3,"part_of_speech":"verb","example_sentence":{"chinese":"我对音乐感兴趣。","pinyin":"wǒ duì yīnyuè gǎn xìngqù.","english":"I am interested in music."}},
  {"id":"hsk3_074","character":"感冒","pinyin":"gǎnmào","translation":"cold, to catch a cold","hsk_level":3,"part_of_speech":"noun","example_sentence":{"chinese":"我感冒了。","pinyin":"wǒ gǎnmào le.","english":"I caught a cold."}},
  {"id":"hsk3_075","character":"刚才","pinyin":"gāngcái","translation":"just now, a moment ago","hsk_level":3,"part_of_speech":"adverb","example_sentence":{"chinese":"刚才他打电话了。","pinyin":"gāngcái tā dǎ diànhuà le.","english":"He just called."}},
  {"id":"hsk3_076","character":"个子","pinyin":"gèzi","translation":"height, stature","hsk_level":3,"part_of_speech":"noun","example_sentence":{"chinese":"他个子很高。","pinyin":"tā gèzi hěn gāo.","english":"He is very tall."}},
  {"id":"hsk3_077","character":"跟","pinyin":"gēn","translation":"with, to follow","hsk_level":3,"part_of_speech":"preposition","example_sentence":{"chinese":"跟我来。","pinyin":"gēn wǒ lái.","english":"Come with me."}},
  {"id":"hsk3_078","character":"根据","pinyin":"gēnjù","translation":"based on, according to","hsk_level":3,"part_of_speech":"preposition","example_sentence":{"chinese":"根据规定。","pinyin":"gēnjù guīdìng.","english":"According to the rules."}},
  {"id":"hsk3_079","character":"更","pinyin":"gèng","translation":"even more, still more","hsk_level":3,"part_of_speech":"adverb","example_sentence":{"chinese":"今天更冷。","pinyin":"jīntiān gèng lěng.","english":"Today is even colder."}},
  {"id":"hsk3_080","character":"公斤","pinyin":"gōngjīn","translation":"kilogram","hsk_level":3,"part_of_speech":"measure_word","example_sentence":{"chinese":"他体重七十公斤。","pinyin":"tā tǐzhòng qīshí gōngjīn.","english":"He weighs seventy kilograms."}},
  {"id":"hsk3_081","character":"公园","pinyin":"gōngyuán","translation":"park","hsk_level":3,"part_of_speech":"noun","example_sentence":{"chinese":"我们去公园散步。","pinyin":"wǒmen qù gōngyuán sànbù.","english":"We go to the park for a walk."}},
  {"id":"hsk3_082","character":"故事","pinyin":"gùshi","translation":"story, tale","hsk_level":3,"part_of_speech":"noun","example_sentence":{"chinese":"她讲了一个故事。","pinyin":"tā jiǎng le yī gè gùshi.","english":"She told a story."}},
  {"id":"hsk3_083","character":"刮风","pinyin":"guā fēng","translation":"to be windy","hsk_level":3,"part_of_speech":"verb","example_sentence":{"chinese":"今天刮风了。","pinyin":"jīntiān guā fēng le.","english":"It is windy today."}},
  {"id":"hsk3_084","character":"关","pinyin":"guān","translation":"to close, to turn off","hsk_level":3,"part_of_speech":"verb","example_sentence":{"chinese":"关门，关灯。","pinyin":"guān mén, guān dēng.","english":"Close the door, turn off the light."}},
  {"id":"hsk3_085","character":"关系","pinyin":"guānxi","translation":"relationship, connection","hsk_level":3,"part_of_speech":"noun","example_sentence":{"chinese":"我们关系很好。","pinyin":"wǒmen guānxi hěn hǎo.","english":"Our relationship is very good."}},
  {"id":"hsk3_086","character":"关心","pinyin":"guānxīn","translation":"to care about, to show concern","hsk_level":3,"part_of_speech":"verb","example_sentence":{"chinese":"他很关心我。","pinyin":"tā hěn guānxīn wǒ.","english":"He cares about me a lot."}},
  {"id":"hsk3_087","character":"关于","pinyin":"guānyú","translation":"about, concerning, regarding","hsk_level":3,"part_of_speech":"preposition","example_sentence":{"chinese":"关于这个问题。","pinyin":"guānyú zhège wèntí.","english":"Regarding this question."}},
  {"id":"hsk3_088","character":"国家","pinyin":"guójiā","translation":"country, nation","hsk_level":3,"part_of_speech":"noun","example_sentence":{"chinese":"中国是大国家。","pinyin":"Zhōngguó shì dà guójiā.","english":"China is a big country."}},
  {"id":"hsk3_089","character":"过去","pinyin":"guòqù","translation":"past, formerly","hsk_level":3,"part_of_speech":"noun","example_sentence":{"chinese":"过去的事情。","pinyin":"guòqù de shìqing.","english":"Past matters."}},
  {"id":"hsk3_090","character":"过","pinyin":"guò","translation":"to pass, to spend (time)","hsk_level":3,"part_of_speech":"verb","example_sentence":{"chinese":"时间过得快。","pinyin":"shíjiān guò de kuài.","english":"Time passes quickly."}},
  {"id":"hsk3_091","character":"还是","pinyin":"háishi","translation":"or (in questions), had better","hsk_level":3,"part_of_speech":"conjunction","example_sentence":{"chinese":"你要茶还是咖啡？","pinyin":"nǐ yào chá háishi kāfēi?","english":"Do you want tea or coffee?"}},
  {"id":"hsk3_092","character":"害怕","pinyin":"hàipà","translation":"to be afraid, to fear","hsk_level":3,"part_of_speech":"verb","example_sentence":{"chinese":"我不害怕。","pinyin":"wǒ bù hàipà.","english":"I am not afraid."}},
  {"id":"hsk3_093","character":"黑板","pinyin":"hēibǎn","translation":"blackboard, chalkboard","hsk_level":3,"part_of_speech":"noun","example_sentence":{"chinese":"老师在黑板上写字。","pinyin":"lǎoshī zài hēibǎn shàng xiě zì.","english":"The teacher writes on the blackboard."}},
  {"id":"hsk3_094","character":"后来","pinyin":"hòulái","translation":"afterwards, later","hsk_level":3,"part_of_speech":"adverb","example_sentence":{"chinese":"后来他回来了。","pinyin":"hòulái tā huílái le.","english":"Afterwards he came back."}},
  {"id":"hsk3_095","character":"护照","pinyin":"hùzhào","translation":"passport","hsk_level":3,"part_of_speech":"noun","example_sentence":{"chinese":"带上你的护照。","pinyin":"dài shàng nǐ de hùzhào.","english":"Bring your passport."}},
  {"id":"hsk3_096","character":"花","pinyin":"huā","translation":"flower; to spend (money/time)","hsk_level":3,"part_of_speech":"noun","example_sentence":{"chinese":"这朵花很漂亮。","pinyin":"zhè duǒ huā hěn piàoliang.","english":"This flower is very beautiful."}},
  {"id":"hsk3_097","character":"画","pinyin":"huà","translation":"painting, picture; to draw","hsk_level":3,"part_of_speech":"noun","example_sentence":{"chinese":"他画了一幅画。","pinyin":"tā huà le yī fú huà.","english":"He drew a painting."}},
  {"id":"hsk3_098","character":"坏","pinyin":"huài","translation":"bad, broken","hsk_level":3,"part_of_speech":"adjective","example_sentence":{"chinese":"这个苹果坏了。","pinyin":"zhège píngguǒ huài le.","english":"This apple has gone bad."}},
  {"id":"hsk3_099","character":"欢迎","pinyin":"huānyíng","translation":"to welcome","hsk_level":3,"part_of_speech":"verb","example_sentence":{"chinese":"欢迎你来中国！","pinyin":"huānyíng nǐ lái Zhōngguó!","english":"Welcome to China!"}},
  {"id":"hsk3_100","character":"还","pinyin":"huán","translation":"to return (something)","hsk_level":3,"part_of_speech":"verb","example_sentence":{"chinese":"还书给图书馆。","pinyin":"huán shū gěi túshūguǎn.","english":"Return the book to the library."}},
  {"id":"hsk3_101","character":"环境","pinyin":"huánjìng","translation":"environment, surroundings","hsk_level":3,"part_of_speech":"noun","example_sentence":{"chinese":"保护环境。","pinyin":"bǎohù huánjìng.","english":"Protect the environment."}},
  {"id":"hsk3_102","character":"换","pinyin":"huàn","translation":"to change, to exchange","hsk_level":3,"part_of_speech":"verb","example_sentence":{"chinese":"我换了新手机。","pinyin":"wǒ huàn le xīn shǒujī.","english":"I changed to a new phone."}},
  {"id":"hsk3_103","character":"回答","pinyin":"huídá","translation":"to answer, to reply","hsk_level":3,"part_of_speech":"verb","example_sentence":{"chinese":"请回答问题。","pinyin":"qǐng huídá wèntí.","english":"Please answer the question."}},
  {"id":"hsk3_104","character":"会议","pinyin":"huìyì","translation":"meeting, conference","hsk_level":3,"part_of_speech":"noun","example_sentence":{"chinese":"下午有会议。","pinyin":"xiàwǔ yǒu huìyì.","english":"There is a meeting in the afternoon."}},
  {"id":"hsk3_105","character":"或者","pinyin":"huòzhě","translation":"or (in statements)","hsk_level":3,"part_of_speech":"conjunction","example_sentence":{"chinese":"你可以走路或者坐车。","pinyin":"nǐ kěyǐ zǒulù huòzhě zuò chē.","english":"You can walk or take a bus."}},
  {"id":"hsk3_106","character":"几乎","pinyin":"jīhū","translation":"almost, nearly","hsk_level":3,"part_of_speech":"adverb","example_sentence":{"chinese":"几乎所有人都来了。","pinyin":"jīhū suǒyǒu rén dōu lái le.","english":"Almost everyone came."}},
  {"id":"hsk3_107","character":"机会","pinyin":"jīhuì","translation":"opportunity, chance","hsk_level":3,"part_of_speech":"noun","example_sentence":{"chinese":"这是个好机会。","pinyin":"zhè shì gè hǎo jīhuì.","english":"This is a good opportunity."}},
  {"id":"hsk3_108","character":"极","pinyin":"jí","translation":"extremely, pole","hsk_level":3,"part_of_speech":"adverb","example_sentence":{"chinese":"好极了！","pinyin":"hǎo jí le!","english":"Extremely good!"}},
  {"id":"hsk3_109","character":"记得","pinyin":"jìde","translation":"to remember","hsk_level":3,"part_of_speech":"verb","example_sentence":{"chinese":"你记得吗？","pinyin":"nǐ jìde ma?","english":"Do you remember?"}},
  {"id":"hsk3_110","character":"季节","pinyin":"jìjié","translation":"season","hsk_level":3,"part_of_speech":"noun","example_sentence":{"chinese":"你最喜欢哪个季节？","pinyin":"nǐ zuì xǐhuān nǎge jìjié?","english":"Which season do you like the most?"}},
  {"id":"hsk3_111","character":"检查","pinyin":"jiǎnchá","translation":"to check, to inspect","hsk_level":3,"part_of_speech":"verb","example_sentence":{"chinese":"医生检查了我。","pinyin":"yīshēng jiǎnchá le wǒ.","english":"The doctor examined me."}},
  {"id":"hsk3_112","character":"简单","pinyin":"jiǎndān","translation":"simple, easy","hsk_level":3,"part_of_speech":"adjective","example_sentence":{"chinese":"这道题很简单。","pinyin":"zhè dào tí hěn jiǎndān.","english":"This question is very simple."}},
  {"id":"hsk3_113","character":"健康","pinyin":"jiànkāng","translation":"healthy, health","hsk_level":3,"part_of_speech":"adjective","example_sentence":{"chinese":"祝你身体健康！","pinyin":"zhù nǐ shēntǐ jiànkāng!","english":"Wish you good health!"}},
  {"id":"hsk3_114","character":"见面","pinyin":"jiànmiàn","translation":"to meet, to see each other","hsk_level":3,"part_of_speech":"verb","example_sentence":{"chinese":"我们明天见面。","pinyin":"wǒmen míngtiān jiànmiàn.","english":"We will meet tomorrow."}},
  {"id":"hsk3_115","character":"讲","pinyin":"jiǎng","translation":"to speak, to explain, to tell","hsk_level":3,"part_of_speech":"verb","example_sentence":{"chinese":"他讲故事很好。","pinyin":"tā jiǎng gùshi hěn hǎo.","english":"He tells stories very well."}},
  {"id":"hsk3_116","character":"教","pinyin":"jiāo","translation":"to teach","hsk_level":3,"part_of_speech":"verb","example_sentence":{"chinese":"她教汉语。","pinyin":"tā jiāo Hànyǔ.","english":"She teaches Chinese."}},
  {"id":"hsk3_117","character":"脚","pinyin":"jiǎo","translation":"foot","hsk_level":3,"part_of_speech":"noun","example_sentence":{"chinese":"我的脚很疼。","pinyin":"wǒ de jiǎo hěn téng.","english":"My foot hurts a lot."}},
  {"id":"hsk3_118","character":"接","pinyin":"jiē","translation":"to receive, to pick up","hsk_level":3,"part_of_speech":"verb","example_sentence":{"chinese":"我去接你。","pinyin":"wǒ qù jiē nǐ.","english":"I'll go pick you up."}},
  {"id":"hsk3_119","character":"街道","pinyin":"jiēdào","translation":"street, road","hsk_level":3,"part_of_speech":"noun","example_sentence":{"chinese":"这条街道很热闹。","pinyin":"zhè tiáo jiēdào hěn rènào.","english":"This street is very lively."}},
  {"id":"hsk3_120","character":"结婚","pinyin":"jiéhūn","translation":"to marry, to get married","hsk_level":3,"part_of_speech":"verb","example_sentence":{"chinese":"他们结婚了。","pinyin":"tāmen jiéhūn le.","english":"They got married."}},
  {"id":"hsk3_121","character":"结束","pinyin":"jiéshù","translation":"to end, to finish","hsk_level":3,"part_of_speech":"verb","example_sentence":{"chinese":"课结束了。","pinyin":"kè jiéshù le.","english":"Class is over."}},
  {"id":"hsk3_122","character":"节目","pinyin":"jiémù","translation":"program, show","hsk_level":3,"part_of_speech":"noun","example_sentence":{"chinese":"这个节目很好看。","pinyin":"zhège jiémù hěn hǎokàn.","english":"This program is very good."}},
  {"id":"hsk3_123","character":"节日","pinyin":"jiérì","translation":"festival, holiday","hsk_level":3,"part_of_speech":"noun","example_sentence":{"chinese":"春节是中国的节日。","pinyin":"Chūnjié shì Zhōngguó de jiérì.","english":"Spring Festival is a Chinese holiday."}},
  {"id":"hsk3_124","character":"解决","pinyin":"jiějué","translation":"to solve, to resolve","hsk_level":3,"part_of_speech":"verb","example_sentence":{"chinese":"我们解决了问题。","pinyin":"wǒmen jiějué le wèntí.","english":"We solved the problem."}},
  {"id":"hsk3_125","character":"借","pinyin":"jiè","translation":"to borrow, to lend","hsk_level":3,"part_of_speech":"verb","example_sentence":{"chinese":"我借了一本书。","pinyin":"wǒ jiè le yī běn shū.","english":"I borrowed a book."}},
  {"id":"hsk3_126","character":"经常","pinyin":"jīngcháng","translation":"often, frequently","hsk_level":3,"part_of_speech":"adverb","example_sentence":{"chinese":"我经常去图书馆。","pinyin":"wǒ jīngcháng qù túshūguǎn.","english":"I often go to the library."}},
  {"id":"hsk3_127","character":"经过","pinyin":"jīngguò","translation":"to pass by, after","hsk_level":3,"part_of_speech":"preposition","example_sentence":{"chinese":"经过一年的努力。","pinyin":"jīngguò yī nián de nǔlì.","english":"After a year of effort."}},
  {"id":"hsk3_128","character":"经理","pinyin":"jīnglǐ","translation":"manager, director","hsk_level":3,"part_of_speech":"noun","example_sentence":{"chinese":"他是公司经理。","pinyin":"tā shì gōngsī jīnglǐ.","english":"He is the company manager."}},
  {"id":"hsk3_129","character":"久","pinyin":"jiǔ","translation":"long time, for a long time","hsk_level":3,"part_of_speech":"adjective","example_sentence":{"chinese":"好久不见！","pinyin":"hǎo jiǔ bù jiàn!","english":"Long time no see!"}},
  {"id":"hsk3_130","character":"旧","pinyin":"jiù","translation":"old, used, worn out","hsk_level":3,"part_of_speech":"adjective","example_sentence":{"chinese":"这是旧书。","pinyin":"zhè shì jiù shū.","english":"This is an old book."}},
  {"id":"hsk3_131","character":"句子","pinyin":"jùzi","translation":"sentence","hsk_level":3,"part_of_speech":"noun","example_sentence":{"chinese":"这个句子很长。","pinyin":"zhège jùzi hěn cháng.","english":"This sentence is very long."}},
  {"id":"hsk3_132","character":"决定","pinyin":"juédìng","translation":"to decide, decision","hsk_level":3,"part_of_speech":"verb","example_sentence":{"chinese":"我决定去北京。","pinyin":"wǒ juédìng qù Běijīng.","english":"I decided to go to Beijing."}},
  {"id":"hsk3_133","character":"渴","pinyin":"kě","translation":"thirsty","hsk_level":3,"part_of_speech":"adjective","example_sentence":{"chinese":"我很渴。","pinyin":"wǒ hěn kě.","english":"I am very thirsty."}},
  {"id":"hsk3_134","character":"可爱","pinyin":"kě'ài","translation":"cute, lovely","hsk_level":3,"part_of_speech":"adjective","example_sentence":{"chinese":"这只猫真可爱。","pinyin":"zhè zhī māo zhēn kě'ài.","english":"This cat is really cute."}},
  {"id":"hsk3_135","character":"刻","pinyin":"kè","translation":"quarter (of an hour), to carve","hsk_level":3,"part_of_speech":"noun","example_sentence":{"chinese":"三点一刻。","pinyin":"sān diǎn yī kè.","english":"A quarter past three."}},
  {"id":"hsk3_136","character":"客人","pinyin":"kèrén","translation":"guest, visitor","hsk_level":3,"part_of_speech":"noun","example_sentence":{"chinese":"家里来了客人。","pinyin":"jiā lǐ lái le kèrén.","english":"Guests came to the house."}},
  {"id":"hsk3_137","character":"空调","pinyin":"kōngtiáo","translation":"air conditioner","hsk_level":3,"part_of_speech":"noun","example_sentence":{"chinese":"打开空调。","pinyin":"dǎkāi kōngtiáo.","english":"Turn on the air conditioner."}},
  {"id":"hsk3_138","character":"口","pinyin":"kǒu","translation":"mouth; (measure word for family members)","hsk_level":3,"part_of_speech":"noun","example_sentence":{"chinese":"他家有三口人。","pinyin":"tā jiā yǒu sān kǒu rén.","english":"His family has three members."}},
  {"id":"hsk3_139","character":"哭","pinyin":"kū","translation":"to cry, to weep","hsk_level":3,"part_of_speech":"verb","example_sentence":{"chinese":"她哭了。","pinyin":"tā kū le.","english":"She cried."}},
  {"id":"hsk3_140","character":"裤子","pinyin":"kùzi","translation":"pants, trousers","hsk_level":3,"part_of_speech":"noun","example_sentence":{"chinese":"他穿黑裤子。","pinyin":"tā chuān hēi kùzi.","english":"He wears black pants."}},
  {"id":"hsk3_141","character":"筷子","pinyin":"kuàizi","translation":"chopsticks","hsk_level":3,"part_of_speech":"noun","example_sentence":{"chinese":"用筷子吃饭。","pinyin":"yòng kuàizi chīfàn.","english":"Eat with chopsticks."}},
  {"id":"hsk3_142","character":"蓝","pinyin":"lán","translation":"blue","hsk_level":3,"part_of_speech":"adjective","example_sentence":{"chinese":"天是蓝色的。","pinyin":"tiān shì lánsè de.","english":"The sky is blue."}},
  {"id":"hsk3_143","character":"老","pinyin":"lǎo","translation":"old (age), always","hsk_level":3,"part_of_speech":"adjective","example_sentence":{"chinese":"他的爷爷很老了。","pinyin":"tā de yéye hěn lǎo le.","english":"His grandfather is very old."}},
  {"id":"hsk3_144","character":"离开","pinyin":"líkāi","translation":"to leave, to depart","hsk_level":3,"part_of_speech":"verb","example_sentence":{"chinese":"他离开了家。","pinyin":"tā líkāi le jiā.","english":"He left home."}},
  {"id":"hsk3_145","character":"礼物","pinyin":"lǐwù","translation":"gift, present","hsk_level":3,"part_of_speech":"noun","example_sentence":{"chinese":"我买了一个礼物。","pinyin":"wǒ mǎi le yī gè lǐwù.","english":"I bought a gift."}},
  {"id":"hsk3_146","character":"历史","pinyin":"lìshǐ","translation":"history","hsk_level":3,"part_of_speech":"noun","example_sentence":{"chinese":"中国有悠久的历史。","pinyin":"Zhōngguó yǒu yōujiǔ de lìshǐ.","english":"China has a long history."}},
  {"id":"hsk3_147","character":"脸","pinyin":"liǎn","translation":"face","hsk_level":3,"part_of_speech":"noun","example_sentence":{"chinese":"她的脸很红。","pinyin":"tā de liǎn hěn hóng.","english":"Her face is very red."}},
  {"id":"hsk3_148","character":"聊天","pinyin":"liáotiān","translation":"to chat, to have a conversation","hsk_level":3,"part_of_speech":"verb","example_sentence":{"chinese":"我们聊天吧。","pinyin":"wǒmen liáotiān ba.","english":"Let's chat."}},
  {"id":"hsk3_149","character":"练习","pinyin":"liànxí","translation":"to practice, exercise","hsk_level":3,"part_of_speech":"verb","example_sentence":{"chinese":"我练习汉语。","pinyin":"wǒ liànxí Hànyǔ.","english":"I practice Chinese."}},
  {"id":"hsk3_150","character":"辆","pinyin":"liàng","translation":"(measure word for vehicles)","hsk_level":3,"part_of_speech":"measure_word","example_sentence":{"chinese":"一辆车。","pinyin":"yī liàng chē.","english":"One car."}},
  {"id":"hsk3_151","character":"了解","pinyin":"liǎojiě","translation":"to understand, to know about","hsk_level":3,"part_of_speech":"verb","example_sentence":{"chinese":"我了解情况。","pinyin":"wǒ liǎojiě qíngkuàng.","english":"I understand the situation."}},
  {"id":"hsk3_152","character":"邻居","pinyin":"línjū","translation":"neighbor","hsk_level":3,"part_of_speech":"noun","example_sentence":{"chinese":"我的邻居很友好。","pinyin":"wǒ de línjū hěn yǒuhǎo.","english":"My neighbors are very friendly."}},
  {"id":"hsk3_153","character":"留学","pinyin":"liúxué","translation":"to study abroad","hsk_level":3,"part_of_speech":"verb","example_sentence":{"chinese":"他在中国留学。","pinyin":"tā zài Zhōngguó liúxué.","english":"He studies in China."}},
  {"id":"hsk3_154","character":"楼","pinyin":"lóu","translation":"building, floor, storey","hsk_level":3,"part_of_speech":"noun","example_sentence":{"chinese":"我住三楼。","pinyin":"wǒ zhù sān lóu.","english":"I live on the third floor."}},
  {"id":"hsk3_155","character":"绿","pinyin":"lǜ","translation":"green","hsk_level":3,"part_of_speech":"adjective","example_sentence":{"chinese":"草是绿色的。","pinyin":"cǎo shì lǜsè de.","english":"Grass is green."}},
  {"id":"hsk3_156","character":"马","pinyin":"mǎ","translation":"horse","hsk_level":3,"part_of_speech":"noun","example_sentence":{"chinese":"他骑马。","pinyin":"tā qí mǎ.","english":"He rides a horse."}},
  {"id":"hsk3_157","character":"马上","pinyin":"mǎshàng","translation":"immediately, right away","hsk_level":3,"part_of_speech":"adverb","example_sentence":{"chinese":"我马上来。","pinyin":"wǒ mǎshàng lái.","english":"I'll be right there."}},
  {"id":"hsk3_158","character":"满意","pinyin":"mǎnyì","translation":"satisfied, content","hsk_level":3,"part_of_speech":"adjective","example_sentence":{"chinese":"我很满意。","pinyin":"wǒ hěn mǎnyì.","english":"I am very satisfied."}},
  {"id":"hsk3_159","character":"帽子","pinyin":"màozi","translation":"hat, cap","hsk_level":3,"part_of_speech":"noun","example_sentence":{"chinese":"他戴了一顶帽子。","pinyin":"tā dài le yī dǐng màozi.","english":"He wore a hat."}},
  {"id":"hsk3_160","character":"面包","pinyin":"miànbāo","translation":"bread","hsk_level":3,"part_of_speech":"noun","example_sentence":{"chinese":"早饭吃面包。","pinyin":"zǎofàn chī miànbāo.","english":"Eat bread for breakfast."}},
  {"id":"hsk3_161","character":"明白","pinyin":"míngbai","translation":"to understand, clear","hsk_level":3,"part_of_speech":"verb","example_sentence":{"chinese":"你明白了吗？","pinyin":"nǐ míngbai le ma?","english":"Do you understand now?"}},
  {"id":"hsk3_162","character":"拿","pinyin":"ná","translation":"to take, to hold, to get","hsk_level":3,"part_of_speech":"verb","example_sentence":{"chinese":"拿书给我。","pinyin":"ná shū gěi wǒ.","english":"Bring the book to me."}},
  {"id":"hsk3_163","character":"奶奶","pinyin":"nǎinai","translation":"grandmother (paternal)","hsk_level":3,"part_of_speech":"noun","example_sentence":{"chinese":"奶奶做了饭。","pinyin":"nǎinai zuò le fàn.","english":"Grandma made a meal."}},
  {"id":"hsk3_164","character":"南","pinyin":"nán","translation":"south","hsk_level":3,"part_of_speech":"noun","example_sentence":{"chinese":"往南走。","pinyin":"wǎng nán zǒu.","english":"Walk south."}},
  {"id":"hsk3_165","character":"难过","pinyin":"nánguò","translation":"sad, unhappy","hsk_level":3,"part_of_speech":"adjective","example_sentence":{"chinese":"她很难过。","pinyin":"tā hěn nánguò.","english":"She is very sad."}},
  {"id":"hsk3_166","character":"年级","pinyin":"niánjí","translation":"grade, school year","hsk_level":3,"part_of_speech":"noun","example_sentence":{"chinese":"你几年级？","pinyin":"nǐ jǐ niánjí?","english":"What grade are you in?"}},
  {"id":"hsk3_167","character":"年轻","pinyin":"niánqīng","translation":"young","hsk_level":3,"part_of_speech":"adjective","example_sentence":{"chinese":"她看起来很年轻。","pinyin":"tā kàn qǐlái hěn niánqīng.","english":"She looks very young."}},
  {"id":"hsk3_168","character":"鸟","pinyin":"niǎo","translation":"bird","hsk_level":3,"part_of_speech":"noun","example_sentence":{"chinese":"树上有一只鸟。","pinyin":"shù shàng yǒu yī zhī niǎo.","english":"There is a bird in the tree."}},
  {"id":"hsk3_169","character":"努力","pinyin":"nǔlì","translation":"to work hard, diligently","hsk_level":3,"part_of_speech":"verb","example_sentence":{"chinese":"他努力学习。","pinyin":"tā nǔlì xuéxí.","english":"He studies diligently."}},
  {"id":"hsk3_170","character":"爬山","pinyin":"pá shān","translation":"to climb a mountain, hiking","hsk_level":3,"part_of_speech":"verb","example_sentence":{"chinese":"周末我们去爬山。","pinyin":"zhōumò wǒmen qù pá shān.","english":"We go hiking on the weekend."}},
  {"id":"hsk3_171","character":"盘子","pinyin":"pánzi","translation":"plate, dish","hsk_level":3,"part_of_speech":"noun","example_sentence":{"chinese":"把菜放在盘子里。","pinyin":"bǎ cài fàng zài pánzi lǐ.","english":"Put the food in the plate."}},
  {"id":"hsk3_172","character":"胖","pinyin":"pàng","translation":"fat, overweight","hsk_level":3,"part_of_speech":"adjective","example_sentence":{"chinese":"他胖了。","pinyin":"tā pàng le.","english":"He got fat."}},
  {"id":"hsk3_173","character":"啤酒","pinyin":"píjiǔ","translation":"beer","hsk_level":3,"part_of_speech":"noun","example_sentence":{"chinese":"他喝了一瓶啤酒。","pinyin":"tā hē le yī píng píjiǔ.","english":"He drank a bottle of beer."}},
  {"id":"hsk3_174","character":"皮鞋","pinyin":"píxié","translation":"leather shoes","hsk_level":3,"part_of_speech":"noun","example_sentence":{"chinese":"他穿了皮鞋。","pinyin":"tā chuān le píxié.","english":"He wore leather shoes."}},
  {"id":"hsk3_175","character":"瓶子","pinyin":"píngzi","translation":"bottle","hsk_level":3,"part_of_speech":"noun","example_sentence":{"chinese":"一瓶水。","pinyin":"yī píng shuǐ.","english":"A bottle of water."}},
  {"id":"hsk3_176","character":"其实","pinyin":"qíshí","translation":"actually, in fact","hsk_level":3,"part_of_speech":"adverb","example_sentence":{"chinese":"其实我不喜欢。","pinyin":"qíshí wǒ bù xǐhuān.","english":"Actually, I don't like it."}},
  {"id":"hsk3_177","character":"其他","pinyin":"qítā","translation":"other, else","hsk_level":3,"part_of_speech":"adjective","example_sentence":{"chinese":"其他人呢？","pinyin":"qítā rén ne?","english":"What about the others?"}},
  {"id":"hsk3_178","character":"骑","pinyin":"qí","translation":"to ride (bicycle/horse)","hsk_level":3,"part_of_speech":"verb","example_sentence":{"chinese":"我骑自行车上班。","pinyin":"wǒ qí zìxíngchē shàngbān.","english":"I ride a bicycle to work."}},
  {"id":"hsk3_179","character":"奇怪","pinyin":"qíguài","translation":"strange, odd","hsk_level":3,"part_of_speech":"adjective","example_sentence":{"chinese":"真奇怪！","pinyin":"zhēn qíguài!","english":"How strange!"}},
  {"id":"hsk3_180","character":"起来","pinyin":"qǐlái","translation":"to get up, to rise","hsk_level":3,"part_of_speech":"verb","example_sentence":{"chinese":"快起来！","pinyin":"kuài qǐlái!","english":"Get up quickly!"}},
  {"id":"hsk3_181","character":"起飞","pinyin":"qǐfēi","translation":"to take off (airplane)","hsk_level":3,"part_of_speech":"verb","example_sentence":{"chinese":"飞机起飞了。","pinyin":"fēijī qǐfēi le.","english":"The airplane took off."}},
  {"id":"hsk3_182","character":"清楚","pinyin":"qīngchu","translation":"clear, distinct","hsk_level":3,"part_of_speech":"adjective","example_sentence":{"chinese":"说清楚一点。","pinyin":"shuō qīngchu yīdiǎn.","english":"Speak more clearly."}},
  {"id":"hsk3_183","character":"请假","pinyin":"qǐngjià","translation":"to ask for leave","hsk_level":3,"part_of_speech":"verb","example_sentence":{"chinese":"我请了一天假。","pinyin":"wǒ qǐng le yī tiān jià.","english":"I took one day off."}},
  {"id":"hsk3_184","character":"秋","pinyin":"qiū","translation":"autumn, fall","hsk_level":3,"part_of_speech":"noun","example_sentence":{"chinese":"秋天树叶变红。","pinyin":"qiūtiān shùyè biàn hóng.","english":"Leaves turn red in autumn."}},
  {"id":"hsk3_185","character":"裙子","pinyin":"qúnzi","translation":"skirt, dress","hsk_level":3,"part_of_speech":"noun","example_sentence":{"chinese":"她穿了一条裙子。","pinyin":"tā chuān le yī tiáo qúnzi.","english":"She wore a skirt."}},
  {"id":"hsk3_186","character":"然后","pinyin":"ránhòu","translation":"then, after that","hsk_level":3,"part_of_speech":"adverb","example_sentence":{"chinese":"先吃饭，然后看电影。","pinyin":"xiān chīfàn, ránhòu kàn diànyǐng.","english":"First eat, then watch a movie."}},
  {"id":"hsk3_187","character":"热情","pinyin":"rèqíng","translation":"enthusiastic, warm","hsk_level":3,"part_of_speech":"adjective","example_sentence":{"chinese":"她非常热情。","pinyin":"tā fēicháng rèqíng.","english":"She is very enthusiastic."}},
  {"id":"hsk3_188","character":"认为","pinyin":"rènwéi","translation":"to think, to believe, to consider","hsk_level":3,"part_of_speech":"verb","example_sentence":{"chinese":"我认为这是对的。","pinyin":"wǒ rènwéi zhè shì duì de.","english":"I think this is correct."}},
  {"id":"hsk3_189","character":"认真","pinyin":"rènzhēn","translation":"serious, conscientious","hsk_level":3,"part_of_speech":"adjective","example_sentence":{"chinese":"他工作很认真。","pinyin":"tā gōngzuò hěn rènzhēn.","english":"He works very seriously."}},
  {"id":"hsk3_190","character":"如果","pinyin":"rúguǒ","translation":"if, in case","hsk_level":3,"part_of_speech":"conjunction","example_sentence":{"chinese":"如果下雨，就不去了。","pinyin":"rúguǒ xià yǔ, jiù bù qù le.","english":"If it rains, we won't go."}},
  {"id":"hsk3_191","character":"伞","pinyin":"sǎn","translation":"umbrella","hsk_level":3,"part_of_speech":"noun","example_sentence":{"chinese":"带伞出门。","pinyin":"dài sǎn chūmén.","english":"Take an umbrella when going out."}},
  {"id":"hsk3_192","character":"上网","pinyin":"shàngwǎng","translation":"to go online, to surf the internet","hsk_level":3,"part_of_speech":"verb","example_sentence":{"chinese":"我在上网查资料。","pinyin":"wǒ zài shàngwǎng chá zīliào.","english":"I am online looking for information."}},
  {"id":"hsk3_193","character":"生气","pinyin":"shēngqì","translation":"angry, to get angry","hsk_level":3,"part_of_speech":"adjective","example_sentence":{"chinese":"别生气！","pinyin":"bié shēngqì!","english":"Don't be angry!"}},
  {"id":"hsk3_194","character":"声音","pinyin":"shēngyīn","translation":"sound, voice","hsk_level":3,"part_of_speech":"noun","example_sentence":{"chinese":"她的声音很好听。","pinyin":"tā de shēngyīn hěn hǎotīng.","english":"Her voice is very pleasant."}},
  {"id":"hsk3_195","character":"试","pinyin":"shì","translation":"to try, to test","hsk_level":3,"part_of_speech":"verb","example_sentence":{"chinese":"试一试！","pinyin":"shì yī shì!","english":"Give it a try!"}},
  {"id":"hsk3_196","character":"世界","pinyin":"shìjiè","translation":"world","hsk_level":3,"part_of_speech":"noun","example_sentence":{"chinese":"世界很大。","pinyin":"shìjiè hěn dà.","english":"The world is very big."}},
  {"id":"hsk3_197","character":"瘦","pinyin":"shòu","translation":"thin, slim","hsk_level":3,"part_of_speech":"adjective","example_sentence":{"chinese":"她变瘦了。","pinyin":"tā biàn shòu le.","english":"She has become thinner."}},
  {"id":"hsk3_198","character":"舒服","pinyin":"shūfu","translation":"comfortable","hsk_level":3,"part_of_speech":"adjective","example_sentence":{"chinese":"这把椅子很舒服。","pinyin":"zhè bǎ yǐzi hěn shūfu.","english":"This chair is very comfortable."}},
  {"id":"hsk3_199","character":"叔叔","pinyin":"shūshu","translation":"uncle (father's younger brother)","hsk_level":3,"part_of_speech":"noun","example_sentence":{"chinese":"叔叔来了。","pinyin":"shūshu lái le.","english":"Uncle came."}},
  {"id":"hsk3_200","character":"树","pinyin":"shù","translation":"tree","hsk_level":3,"part_of_speech":"noun","example_sentence":{"chinese":"公园里有很多树。","pinyin":"gōngyuán lǐ yǒu hěn duō shù.","english":"There are many trees in the park."}},
  {"id":"hsk3_201","character":"数学","pinyin":"shùxué","translation":"mathematics","hsk_level":3,"part_of_speech":"noun","example_sentence":{"chinese":"他数学很好。","pinyin":"tā shùxué hěn hǎo.","english":"He is good at mathematics."}},
  {"id":"hsk3_202","character":"刷牙","pinyin":"shuā yá","translation":"to brush teeth","hsk_level":3,"part_of_speech":"verb","example_sentence":{"chinese":"每天刷牙。","pinyin":"měi tiān shuā yá.","english":"Brush teeth every day."}},
  {"id":"hsk3_203","character":"双","pinyin":"shuāng","translation":"pair, double","hsk_level":3,"part_of_speech":"measure_word","example_sentence":{"chinese":"一双筷子。","pinyin":"yī shuāng kuàizi.","english":"A pair of chopsticks."}},
  {"id":"hsk3_204","character":"水平","pinyin":"shuǐpíng","translation":"level, standard","hsk_level":3,"part_of_speech":"noun","example_sentence":{"chinese":"他的汉语水平很高。","pinyin":"tā de Hànyǔ shuǐpíng hěn gāo.","english":"His Chinese level is very high."}},
  {"id":"hsk3_205","character":"司机","pinyin":"sījī","translation":"driver, chauffeur","hsk_level":3,"part_of_speech":"noun","example_sentence":{"chinese":"司机开车很快。","pinyin":"sījī kāi chē hěn kuài.","english":"The driver drives very fast."}},
  {"id":"hsk3_206","character":"太阳","pinyin":"tàiyáng","translation":"sun","hsk_level":3,"part_of_speech":"noun","example_sentence":{"chinese":"今天太阳很大。","pinyin":"jīntiān tàiyáng hěn dà.","english":"The sun is very strong today."}},
  {"id":"hsk3_207","character":"特别","pinyin":"tèbié","translation":"especially, particularly","hsk_level":3,"part_of_speech":"adverb","example_sentence":{"chinese":"我特别喜欢音乐。","pinyin":"wǒ tèbié xǐhuān yīnyuè.","english":"I especially like music."}},
  {"id":"hsk3_208","character":"疼","pinyin":"téng","translation":"to hurt, to ache","hsk_level":3,"part_of_speech":"verb","example_sentence":{"chinese":"我头疼。","pinyin":"wǒ tóuténg.","english":"I have a headache."}},
  {"id":"hsk3_209","character":"提高","pinyin":"tígāo","translation":"to improve, to raise","hsk_level":3,"part_of_speech":"verb","example_sentence":{"chinese":"提高成绩。","pinyin":"tígāo chéngjì.","english":"Improve grades."}},
  {"id":"hsk3_210","character":"体育","pinyin":"tǐyù","translation":"sports, physical education","hsk_level":3,"part_of_speech":"noun","example_sentence":{"chinese":"我喜欢体育课。","pinyin":"wǒ xǐhuān tǐyù kè.","english":"I like PE class."}},
  {"id":"hsk3_211","character":"甜","pinyin":"tián","translation":"sweet","hsk_level":3,"part_of_speech":"adjective","example_sentence":{"chinese":"这个蛋糕很甜。","pinyin":"zhège dàngāo hěn tián.","english":"This cake is very sweet."}},
  {"id":"hsk3_212","character":"条","pinyin":"tiáo","translation":"(measure word for long thin things)","hsk_level":3,"part_of_speech":"measure_word","example_sentence":{"chinese":"一条鱼。","pinyin":"yī tiáo yú.","english":"One fish."}},
  {"id":"hsk3_213","character":"同事","pinyin":"tóngshì","translation":"colleague, coworker","hsk_level":3,"part_of_speech":"noun","example_sentence":{"chinese":"他是我的同事。","pinyin":"tā shì wǒ de tóngshì.","english":"He is my colleague."}},
  {"id":"hsk3_214","character":"同意","pinyin":"tóngyì","translation":"to agree, to approve","hsk_level":3,"part_of_speech":"verb","example_sentence":{"chinese":"我同意你的看法。","pinyin":"wǒ tóngyì nǐ de kànfǎ.","english":"I agree with your opinion."}},
  {"id":"hsk3_215","character":"头发","pinyin":"tóufa","translation":"hair (on head)","hsk_level":3,"part_of_speech":"noun","example_sentence":{"chinese":"她的头发很长。","pinyin":"tā de tóufa hěn cháng.","english":"Her hair is very long."}},
  {"id":"hsk3_216","character":"突然","pinyin":"tūrán","translation":"suddenly, unexpectedly","hsk_level":3,"part_of_speech":"adverb","example_sentence":{"chinese":"突然下雨了。","pinyin":"tūrán xià yǔ le.","english":"It suddenly rained."}},
  {"id":"hsk3_217","character":"图书馆","pinyin":"túshūguǎn","translation":"library","hsk_level":3,"part_of_speech":"noun","example_sentence":{"chinese":"我在图书馆看书。","pinyin":"wǒ zài túshūguǎn kàn shū.","english":"I read in the library."}},
  {"id":"hsk3_218","character":"腿","pinyin":"tuǐ","translation":"leg","hsk_level":3,"part_of_speech":"noun","example_sentence":{"chinese":"他的腿受伤了。","pinyin":"tā de tuǐ shòushāng le.","english":"His leg was injured."}},
  {"id":"hsk3_219","character":"完成","pinyin":"wánchéng","translation":"to complete, to finish","hsk_level":3,"part_of_speech":"verb","example_sentence":{"chinese":"完成作业。","pinyin":"wánchéng zuòyè.","english":"Complete the homework."}},
  {"id":"hsk3_220","character":"碗","pinyin":"wǎn","translation":"bowl","hsk_level":3,"part_of_speech":"noun","example_sentence":{"chinese":"一碗米饭。","pinyin":"yī wǎn mǐfàn.","english":"A bowl of rice."}},
  {"id":"hsk3_221","character":"万","pinyin":"wàn","translation":"ten thousand","hsk_level":3,"part_of_speech":"numeral","example_sentence":{"chinese":"一万人。","pinyin":"yī wàn rén.","english":"Ten thousand people."}},
  {"id":"hsk3_222","character":"忘记","pinyin":"wàngjì","translation":"to forget","hsk_level":3,"part_of_speech":"verb","example_sentence":{"chinese":"我忘记了。","pinyin":"wǒ wàngjì le.","english":"I forgot."}},
  {"id":"hsk3_223","character":"为","pinyin":"wèi","translation":"for, because of","hsk_level":3,"part_of_speech":"preposition","example_sentence":{"chinese":"为你高兴。","pinyin":"wèi nǐ gāoxìng.","english":"Happy for you."}},
  {"id":"hsk3_224","character":"为了","pinyin":"wèile","translation":"in order to, for the sake of","hsk_level":3,"part_of_speech":"preposition","example_sentence":{"chinese":"为了健康要运动。","pinyin":"wèile jiànkāng yào yùndòng.","english":"In order to be healthy, exercise."}},
  {"id":"hsk3_225","character":"位","pinyin":"wèi","translation":"(polite measure word for people)","hsk_level":3,"part_of_speech":"measure_word","example_sentence":{"chinese":"这位是王老师。","pinyin":"zhè wèi shì Wáng lǎoshī.","english":"This is Teacher Wang."}},
  {"id":"hsk3_226","character":"文化","pinyin":"wénhuà","translation":"culture","hsk_level":3,"part_of_speech":"noun","example_sentence":{"chinese":"中国文化很有意思。","pinyin":"Zhōngguó wénhuà hěn yǒu yìsi.","english":"Chinese culture is very interesting."}},
  {"id":"hsk3_227","character":"西","pinyin":"xī","translation":"west","hsk_level":3,"part_of_speech":"noun","example_sentence":{"chinese":"往西走。","pinyin":"wǎng xī zǒu.","english":"Walk west."}},
  {"id":"hsk3_228","character":"习惯","pinyin":"xíguàn","translation":"habit, custom; to be used to","hsk_level":3,"part_of_speech":"noun","example_sentence":{"chinese":"这是个好习惯。","pinyin":"zhè shì gè hǎo xíguàn.","english":"This is a good habit."}},
  {"id":"hsk3_229","character":"洗手间","pinyin":"xǐshǒujiān","translation":"restroom, bathroom","hsk_level":3,"part_of_speech":"noun","example_sentence":{"chinese":"洗手间在哪里？","pinyin":"xǐshǒujiān zài nǎlǐ?","english":"Where is the restroom?"}},
  {"id":"hsk3_230","character":"洗澡","pinyin":"xǐzǎo","translation":"to take a shower/bath","hsk_level":3,"part_of_speech":"verb","example_sentence":{"chinese":"我去洗澡。","pinyin":"wǒ qù xǐzǎo.","english":"I am going to take a shower."}},
  {"id":"hsk3_231","character":"夏","pinyin":"xià","translation":"summer","hsk_level":3,"part_of_speech":"noun","example_sentence":{"chinese":"夏天很热。","pinyin":"xiàtiān hěn rè.","english":"Summer is very hot."}},
  {"id":"hsk3_232","character":"先","pinyin":"xiān","translation":"first, before","hsk_level":3,"part_of_speech":"adverb","example_sentence":{"chinese":"先吃饭。","pinyin":"xiān chīfàn.","english":"Eat first."}},
  {"id":"hsk3_233","character":"香蕉","pinyin":"xiāngjiāo","translation":"banana","hsk_level":3,"part_of_speech":"noun","example_sentence":{"chinese":"我喜欢吃香蕉。","pinyin":"wǒ xǐhuān chī xiāngjiāo.","english":"I like to eat bananas."}},
  {"id":"hsk3_234","character":"相信","pinyin":"xiāngxìn","translation":"to believe, to trust","hsk_level":3,"part_of_speech":"verb","example_sentence":{"chinese":"我相信你。","pinyin":"wǒ xiāngxìn nǐ.","english":"I believe you."}},
  {"id":"hsk3_235","character":"向","pinyin":"xiàng","translation":"toward, facing","hsk_level":3,"part_of_speech":"preposition","example_sentence":{"chinese":"向右转。","pinyin":"xiàng yòu zhuǎn.","english":"Turn right."}},
  {"id":"hsk3_236","character":"像","pinyin":"xiàng","translation":"to be like, to resemble","hsk_level":3,"part_of_speech":"verb","example_sentence":{"chinese":"他像他爸爸。","pinyin":"tā xiàng tā bàba.","english":"He looks like his father."}},
  {"id":"hsk3_237","character":"小心","pinyin":"xiǎoxīn","translation":"to be careful, careful","hsk_level":3,"part_of_speech":"verb","example_sentence":{"chinese":"小心！","pinyin":"xiǎoxīn!","english":"Be careful!"}},
  {"id":"hsk3_238","character":"校长","pinyin":"xiàozhǎng","translation":"principal, school head","hsk_level":3,"part_of_speech":"noun","example_sentence":{"chinese":"校长今天来了。","pinyin":"xiàozhǎng jīntiān lái le.","english":"The principal came today."}},
  {"id":"hsk3_239","character":"新闻","pinyin":"xīnwén","translation":"news","hsk_level":3,"part_of_speech":"noun","example_sentence":{"chinese":"我看新闻。","pinyin":"wǒ kàn xīnwén.","english":"I watch the news."}},
  {"id":"hsk3_240","character":"新鲜","pinyin":"xīnxiān","translation":"fresh","hsk_level":3,"part_of_speech":"adjective","example_sentence":{"chinese":"这个水果很新鲜。","pinyin":"zhège shuǐguǒ hěn xīnxiān.","english":"This fruit is very fresh."}},
  {"id":"hsk3_241","character":"信用卡","pinyin":"xìnyòngkǎ","translation":"credit card","hsk_level":3,"part_of_speech":"noun","example_sentence":{"chinese":"可以用信用卡吗？","pinyin":"kěyǐ yòng xìnyòngkǎ ma?","english":"Can I pay by credit card?"}},
  {"id":"hsk3_242","character":"行李箱","pinyin":"xínglǐxiāng","translation":"suitcase, luggage","hsk_level":3,"part_of_speech":"noun","example_sentence":{"chinese":"我的行李箱很重。","pinyin":"wǒ de xínglǐxiāng hěn zhòng.","english":"My suitcase is very heavy."}},
  {"id":"hsk3_243","character":"熊猫","pinyin":"xióngmāo","translation":"panda","hsk_level":3,"part_of_speech":"noun","example_sentence":{"chinese":"熊猫是中国的国宝。","pinyin":"xióngmāo shì Zhōngguó de guóbǎo.","english":"The panda is China's national treasure."}},
  {"id":"hsk3_244","character":"需要","pinyin":"xūyào","translation":"to need, to require","hsk_level":3,"part_of_speech":"verb","example_sentence":{"chinese":"我需要帮助。","pinyin":"wǒ xūyào bāngzhù.","english":"I need help."}},
  {"id":"hsk3_245","character":"选择","pinyin":"xuǎnzé","translation":"to choose, choice","hsk_level":3,"part_of_speech":"verb","example_sentence":{"chinese":"你自己选择。","pinyin":"nǐ zìjǐ xuǎnzé.","english":"Make your own choice."}},
  {"id":"hsk3_246","character":"要求","pinyin":"yāoqiú","translation":"requirement, to require","hsk_level":3,"part_of_speech":"noun","example_sentence":{"chinese":"这是基本要求。","pinyin":"zhè shì jīběn yāoqiú.","english":"This is a basic requirement."}},
  {"id":"hsk3_247","character":"爷爷","pinyin":"yéye","translation":"grandfather (paternal)","hsk_level":3,"part_of_speech":"noun","example_sentence":{"chinese":"爷爷很健康。","pinyin":"yéye hěn jiànkāng.","english":"Grandfather is very healthy."}},
  {"id":"hsk3_248","character":"一定","pinyin":"yīdìng","translation":"certainly, definitely","hsk_level":3,"part_of_speech":"adverb","example_sentence":{"chinese":"我一定来。","pinyin":"wǒ yīdìng lái.","english":"I will definitely come."}},
  {"id":"hsk3_249","character":"一共","pinyin":"yīgòng","translation":"altogether, in total","hsk_level":3,"part_of_speech":"adverb","example_sentence":{"chinese":"一共多少钱？","pinyin":"yīgòng duōshǎo qián?","english":"How much in total?"}},
  {"id":"hsk3_250","character":"一会儿","pinyin":"yīhuìr","translation":"a moment, a while","hsk_level":3,"part_of_speech":"noun","example_sentence":{"chinese":"等一会儿。","pinyin":"děng yīhuìr.","english":"Wait a moment."}},
  {"id":"hsk3_251","character":"一样","pinyin":"yīyàng","translation":"same, alike","hsk_level":3,"part_of_speech":"adjective","example_sentence":{"chinese":"我们一样高。","pinyin":"wǒmen yīyàng gāo.","english":"We are the same height."}},
  {"id":"hsk3_252","character":"以前","pinyin":"yǐqián","translation":"before, previously","hsk_level":3,"part_of_speech":"noun","example_sentence":{"chinese":"以前我住在北京。","pinyin":"yǐqián wǒ zhù zài Běijīng.","english":"I used to live in Beijing."}},
  {"id":"hsk3_253","character":"一般","pinyin":"yìbān","translation":"generally, ordinary","hsk_level":3,"part_of_speech":"adverb","example_sentence":{"chinese":"一般情况下。","pinyin":"yìbān qíngkuàng xià.","english":"Under normal circumstances."}},
  {"id":"hsk3_254","character":"一边","pinyin":"yībiān","translation":"one side; while (doing something)","hsk_level":3,"part_of_speech":"noun","example_sentence":{"chinese":"一边吃饭一边看电视。","pinyin":"yībiān chīfàn yībiān kàn diànshì.","english":"Eating while watching TV."}},
  {"id":"hsk3_255","character":"一直","pinyin":"yīzhí","translation":"always, continuously, straight","hsk_level":3,"part_of_speech":"adverb","example_sentence":{"chinese":"一直走。","pinyin":"yīzhí zǒu.","english":"Go straight ahead."}},
  {"id":"hsk3_256","character":"音乐","pinyin":"yīnyuè","translation":"music","hsk_level":3,"part_of_speech":"noun","example_sentence":{"chinese":"我喜欢听音乐。","pinyin":"wǒ xǐhuān tīng yīnyuè.","english":"I like to listen to music."}},
  {"id":"hsk3_257","character":"银行","pinyin":"yínháng","translation":"bank","hsk_level":3,"part_of_speech":"noun","example_sentence":{"chinese":"我去银行取钱。","pinyin":"wǒ qù yínháng qǔ qián.","english":"I go to the bank to withdraw money."}},
  {"id":"hsk3_258","character":"饮料","pinyin":"yǐnliào","translation":"drink, beverage","hsk_level":3,"part_of_speech":"noun","example_sentence":{"chinese":"你要什么饮料？","pinyin":"nǐ yào shénme yǐnliào?","english":"What drink do you want?"}},
  {"id":"hsk3_259","character":"应该","pinyin":"yīnggāi","translation":"should, ought to","hsk_level":3,"part_of_speech":"verb","example_sentence":{"chinese":"你应该早睡。","pinyin":"nǐ yīnggāi zǎo shuì.","english":"You should sleep early."}},
  {"id":"hsk3_260","character":"影响","pinyin":"yǐngxiǎng","translation":"to influence, influence","hsk_level":3,"part_of_speech":"verb","example_sentence":{"chinese":"天气影响心情。","pinyin":"tiānqì yǐngxiǎng xīnqíng.","english":"Weather affects mood."}},
  {"id":"hsk3_261","character":"用","pinyin":"yòng","translation":"to use","hsk_level":3,"part_of_speech":"verb","example_sentence":{"chinese":"我用筷子吃饭。","pinyin":"wǒ yòng kuàizi chīfàn.","english":"I eat with chopsticks."}},
  {"id":"hsk3_262","character":"游戏","pinyin":"yóuxì","translation":"game, to play","hsk_level":3,"part_of_speech":"noun","example_sentence":{"chinese":"孩子们玩游戏。","pinyin":"háizimen wán yóuxì.","english":"The children play games."}},
  {"id":"hsk3_263","character":"有名","pinyin":"yǒumíng","translation":"famous, well-known","hsk_level":3,"part_of_speech":"adjective","example_sentence":{"chinese":"这里很有名。","pinyin":"zhèlǐ hěn yǒumíng.","english":"This place is very famous."}},
  {"id":"hsk3_264","character":"又","pinyin":"yòu","translation":"again, once more","hsk_level":3,"part_of_speech":"adverb","example_sentence":{"chinese":"他又来了。","pinyin":"tā yòu lái le.","english":"He came again."}},
  {"id":"hsk3_265","character":"遇到","pinyin":"yùdào","translation":"to encounter, to meet by chance","hsk_level":3,"part_of_speech":"verb","example_sentence":{"chinese":"我遇到了老朋友。","pinyin":"wǒ yùdào le lǎo péngyǒu.","english":"I ran into an old friend."}},
  {"id":"hsk3_266","character":"元","pinyin":"yuán","translation":"yuan (monetary unit)","hsk_level":3,"part_of_speech":"measure_word","example_sentence":{"chinese":"五十元。","pinyin":"wǔshí yuán.","english":"Fifty yuan."}},
  {"id":"hsk3_267","character":"愿意","pinyin":"yuànyì","translation":"willing to, to be willing","hsk_level":3,"part_of_speech":"verb","example_sentence":{"chinese":"我愿意帮忙。","pinyin":"wǒ yuànyì bāngmáng.","english":"I am willing to help."}},
  {"id":"hsk3_268","character":"月亮","pinyin":"yuèliang","translation":"moon","hsk_level":3,"part_of_speech":"noun","example_sentence":{"chinese":"今晚的月亮很圆。","pinyin":"jīn wǎn de yuèliang hěn yuán.","english":"Tonight's moon is very round."}},
  {"id":"hsk3_269","character":"越","pinyin":"yuè","translation":"the more...the more","hsk_level":3,"part_of_speech":"adverb","example_sentence":{"chinese":"越来越好。","pinyin":"yuè lái yuè hǎo.","english":"Getting better and better."}},
  {"id":"hsk3_270","character":"站","pinyin":"zhàn","translation":"station, stop; to stand","hsk_level":3,"part_of_speech":"noun","example_sentence":{"chinese":"下一站是哪里？","pinyin":"xià yī zhàn shì nǎlǐ?","english":"What is the next station?"}},
  {"id":"hsk3_271","character":"张","pinyin":"zhāng","translation":"(measure word for flat objects)","hsk_level":3,"part_of_speech":"measure_word","example_sentence":{"chinese":"一张纸。","pinyin":"yī zhāng zhǐ.","english":"One piece of paper."}},
  {"id":"hsk3_272","character":"着急","pinyin":"zháojí","translation":"to be anxious, to worry","hsk_level":3,"part_of_speech":"verb","example_sentence":{"chinese":"别着急。","pinyin":"bié zháojí.","english":"Don't be anxious."}},
  {"id":"hsk3_273","character":"照顾","pinyin":"zhàogù","translation":"to look after, to take care of","hsk_level":3,"part_of_speech":"verb","example_sentence":{"chinese":"照顾好自己。","pinyin":"zhàogù hǎo zìjǐ.","english":"Take good care of yourself."}},
  {"id":"hsk3_274","character":"照片","pinyin":"zhàopiàn","translation":"photo, photograph","hsk_level":3,"part_of_speech":"noun","example_sentence":{"chinese":"拍一张照片。","pinyin":"pāi yī zhāng zhàopiàn.","english":"Take a photo."}},
  {"id":"hsk3_275","character":"照相机","pinyin":"zhàoxiàngjī","translation":"camera","hsk_level":3,"part_of_speech":"noun","example_sentence":{"chinese":"用照相机拍照。","pinyin":"yòng zhàoxiàngjī pāi zhào.","english":"Take photos with a camera."}},
  {"id":"hsk3_276","character":"只","pinyin":"zhǐ","translation":"only, merely","hsk_level":3,"part_of_speech":"adverb","example_sentence":{"chinese":"我只有一本书。","pinyin":"wǒ zhǐ yǒu yī běn shū.","english":"I only have one book."}},
  {"id":"hsk3_277","character":"中文","pinyin":"Zhōngwén","translation":"Chinese (language/writing)","hsk_level":3,"part_of_speech":"noun","example_sentence":{"chinese":"我在学中文。","pinyin":"wǒ zài xué Zhōngwén.","english":"I am learning Chinese."}},
  {"id":"hsk3_278","character":"中间","pinyin":"zhōngjiān","translation":"middle, center","hsk_level":3,"part_of_speech":"noun","example_sentence":{"chinese":"在中间等我。","pinyin":"zài zhōngjiān děng wǒ.","english":"Wait for me in the middle."}},
  {"id":"hsk3_279","character":"终于","pinyin":"zhōngyú","translation":"finally, at last","hsk_level":3,"part_of_speech":"adverb","example_sentence":{"chinese":"终于完成了！","pinyin":"zhōngyú wánchéng le!","english":"Finally done!"}},
  {"id":"hsk3_280","character":"种","pinyin":"zhǒng","translation":"kind, type, species","hsk_level":3,"part_of_speech":"measure_word","example_sentence":{"chinese":"各种颜色。","pinyin":"gè zhǒng yánsè.","english":"All kinds of colors."}},
  {"id":"hsk3_281","character":"重要","pinyin":"zhòngyào","translation":"important","hsk_level":3,"part_of_speech":"adjective","example_sentence":{"chinese":"这很重要。","pinyin":"zhè hěn zhòngyào.","english":"This is very important."}},
  {"id":"hsk3_282","character":"周末","pinyin":"zhōumò","translation":"weekend","hsk_level":3,"part_of_speech":"noun","example_sentence":{"chinese":"周末你有什么计划？","pinyin":"zhōumò nǐ yǒu shénme jìhuà?","english":"What are your plans for the weekend?"}},
  {"id":"hsk3_283","character":"主要","pinyin":"zhǔyào","translation":"main, principal","hsk_level":3,"part_of_speech":"adjective","example_sentence":{"chinese":"主要原因是什么？","pinyin":"zhǔyào yuányīn shì shénme?","english":"What is the main reason?"}},
  {"id":"hsk3_284","character":"注意","pinyin":"zhùyì","translation":"to pay attention, to watch out","hsk_level":3,"part_of_speech":"verb","example_sentence":{"chinese":"请注意安全。","pinyin":"qǐng zhùyì ānquán.","english":"Please pay attention to safety."}},
  {"id":"hsk3_285","character":"自己","pinyin":"zìjǐ","translation":"oneself, self","hsk_level":3,"part_of_speech":"pronoun","example_sentence":{"chinese":"你自己去吧。","pinyin":"nǐ zìjǐ qù ba.","english":"Go by yourself."}},
  {"id":"hsk3_286","character":"自行车","pinyin":"zìxíngchē","translation":"bicycle","hsk_level":3,"part_of_speech":"noun","example_sentence":{"chinese":"我骑自行车上学。","pinyin":"wǒ qí zìxíngchē shàng xué.","english":"I ride a bicycle to school."}},
  {"id":"hsk3_287","character":"总是","pinyin":"zǒngshì","translation":"always, constantly","hsk_level":3,"part_of_speech":"adverb","example_sentence":{"chinese":"他总是迟到。","pinyin":"tā zǒngshì chídào.","english":"He is always late."}},
  {"id":"hsk3_288","character":"嘴","pinyin":"zuǐ","translation":"mouth","hsk_level":3,"part_of_speech":"noun","example_sentence":{"chinese":"请闭嘴。","pinyin":"qǐng bì zuǐ.","english":"Please be quiet."}},
  {"id":"hsk3_289","character":"最后","pinyin":"zuìhòu","translation":"last, final","hsk_level":3,"part_of_speech":"adverb","example_sentence":{"chinese":"最后一个问题。","pinyin":"zuìhòu yī gè wèntí.","english":"The last question."}},
  {"id":"hsk3_290","character":"最近","pinyin":"zuìjìn","translation":"recently, lately","hsk_level":3,"part_of_speech":"adverb","example_sentence":{"chinese":"最近你好吗？","pinyin":"zuìjìn nǐ hǎo ma?","english":"How have you been recently?"}},
  {"id":"hsk3_291","character":"作业","pinyin":"zuòyè","translation":"homework, assignment","hsk_level":3,"part_of_speech":"noun","example_sentence":{"chinese":"我做完作业了。","pinyin":"wǒ zuò wán zuòyè le.","english":"I finished my homework."}},
  {"id":"hsk3_292","character":"角","pinyin":"jiǎo","translation":"corner, 10 cents","hsk_level":3,"part_of_speech":"measure_word","example_sentence":{"chinese":"五角钱。","pinyin":"wǔ jiǎo qián.","english":"Fifty cents."}},
  {"id":"hsk3_293","character":"米","pinyin":"mǐ","translation":"meter; rice (uncooked)","hsk_level":3,"part_of_speech":"measure_word","example_sentence":{"chinese":"两米高。","pinyin":"liǎng mǐ gāo.","english":"Two meters tall."}},
  {"id":"hsk3_294","character":"黄河","pinyin":"Huáng Hé","translation":"Yellow River","hsk_level":3,"part_of_speech":"noun","example_sentence":{"chinese":"黄河是中国的母亲河。","pinyin":"Huáng Hé shì Zhōngguó de mǔqīn hé.","english":"The Yellow River is China's mother river."}},
  {"id":"hsk3_295","character":"长","pinyin":"zhǎng","translation":"to grow, elder","hsk_level":3,"part_of_speech":"verb","example_sentence":{"chinese":"孩子长高了。","pinyin":"háizi zhǎng gāo le.","english":"The child has grown taller."}},
  {"id":"hsk3_296","character":"只","pinyin":"zhī","translation":"(measure word for animals)","hsk_level":3,"part_of_speech":"measure_word","example_sentence":{"chinese":"一只猫。","pinyin":"yī zhī māo.","english":"One cat."}},
  {"id":"hsk3_297","character":"只有……才……","pinyin":"zhǐyǒu…cái…","translation":"only if...then...","hsk_level":3,"part_of_speech":"conjunction","example_sentence":{"chinese":"只有努力才能成功。","pinyin":"zhǐyǒu nǔlì cái néng chénggōng.","english":"Only by working hard can you succeed."}},
  {"id":"hsk3_298","character":"帮忙","pinyin":"bāngmáng","translation":"to help out","hsk_level":3,"part_of_speech":"verb","example_sentence":{"chinese":"能帮忙吗？","pinyin":"néng bāngmáng ma?","english":"Can you help?"}},
  {"id":"hsk3_299","character":"花","pinyin":"huā","translation":"to spend (money/time)","hsk_level":3,"part_of_speech":"verb","example_sentence":{"chinese":"花了很多时间。","pinyin":"huā le hěn duō shíjiān.","english":"Spent a lot of time."}},
  {"id":"hsk3_300","character":"过","pinyin":"guò","translation":"to pass, to cross","hsk_level":3,"part_of_speech":"verb","example_sentence":{"chinese":"过马路小心。","pinyin":"guò mǎlù xiǎoxīn.","english":"Be careful crossing the road."}}
]
